colourettu/__init__.py
colourettu/_colour.py
colourettu/_palette.py
colourettu/__pycache__/__init__.cpython-35.pyc
colourettu/__pycache__/_colour.cpython-35.pyc
colourettu/__pycache__/_palette.cpython-35.pyc
colourettu/test/__init__.py
colourettu/test/requirements.txt
colourettu/test/test_colour.py
colourettu/test/test_palette.py
colourettu/test/test_setup.py
colourettu/test/__pycache__/__init__.cpython-35.pyc
colourettu/test/__pycache__/test_colour.cpython-35.pyc
colourettu/test/__pycache__/test_palette.cpython-35.pyc
colourettu/test/__pycache__/test_setup.cpython-35.pyc
colourettu-2.0.0.dist-info/DESCRIPTION.rst
colourettu-2.0.0.dist-info/LICENSE.txt
colourettu-2.0.0.dist-info/METADATA
colourettu-2.0.0.dist-info/RECORD
colourettu-2.0.0.dist-info/WHEEL
colourettu-2.0.0.dist-info/metadata.json
colourettu-2.0.0.dist-info/top_level.txt
