Metadata-Version: 2.0
Name: colourettu
Version: 2.0.0
Summary: Colourettu is a collection of colour related functions.
Home-page: http://minchin.ca/colourettu/
Author: William Minchin
Author-email: w_minchin@hotmail.com
License: MIT License
Platform: any
Classifier: Development Status :: 5 - Production/Stable
Classifier: Programming Language :: Python :: 3
Classifier: Programming Language :: Python :: 3.2
Classifier: Programming Language :: Python :: 3.3
Classifier: Programming Language :: Python :: 3.4
Classifier: Programming Language :: Python :: 3.5
Classifier: Programming Language :: Python :: 3.6
Classifier: Natural Language :: English
Classifier: Environment :: Web Environment
Classifier: Intended Audience :: Developers
Classifier: Operating System :: OS Independent
Classifier: Topic :: Software Development :: Libraries :: Python Modules
Classifier: Topic :: Multimedia :: Graphics
Classifier: License :: OSI Approved :: MIT License
Requires-Dist: Pillow
Provides-Extra: all
Requires-Dist: Babel (!=2.0,>=1.3); extra == 'all'
Requires-Dist: check-manifest; extra == 'all'
Requires-Dist: cloud-sptheme (>=1.8); extra == 'all'
Requires-Dist: coverage; extra == 'all'
Requires-Dist: green (>=1.9.4); extra == 'all'
Requires-Dist: isort; extra == 'all'
Requires-Dist: pip; extra == 'all'
Requires-Dist: pycodestyle; extra == 'all'
Requires-Dist: pydocstyle; extra == 'all'
Requires-Dist: releases; extra == 'all'
Requires-Dist: setuptools (>=18.0); extra == 'all'
Requires-Dist: sphinx (>=1.4); extra == 'all'
Requires-Dist: twine; extra == 'all'
Requires-Dist: wheel; extra == 'all'
Provides-Extra: build
Requires-Dist: pip; extra == 'build'
Requires-Dist: setuptools (>=18.0); extra == 'build'
Requires-Dist: twine; extra == 'build'
Requires-Dist: wheel; extra == 'build'
Provides-Extra: docs
Requires-Dist: Babel (!=2.0,>=1.3); extra == 'docs'
Requires-Dist: cloud-sptheme (>=1.8); extra == 'docs'
Requires-Dist: releases; extra == 'docs'
Requires-Dist: sphinx (>=1.4); extra == 'docs'
Provides-Extra: test
Requires-Dist: check-manifest; extra == 'test'
Requires-Dist: coverage; extra == 'test'
Requires-Dist: green (>=1.9.4); extra == 'test'
Requires-Dist: isort; extra == 'test'
Requires-Dist: pycodestyle; extra == 'test'
Requires-Dist: pydocstyle; extra == 'test'
